geoinsights_3d/__init__.py
geoinsights_3d/__main__.py
geoinsights_3d/analysis.py
geoinsights_3d/app.py
geoinsights_3d/data_processing.py
geoinsights_3d/llm_integration.py
geoinsights_3d/plotting.py
geoinsights_3d/utils.py
geoinsights_3d/assets/3DA logo.png
geoinsights_3d/demo_data/Drill_hole_geochemistry.csv
geoinsights_3d/demo_data/Drill_hole_lithology.csv
geoinsights_3d/demo_data/Drill_hole_lithology_dictionary.csv
geoinsights_3d/demo_data/Drill_hole_location.csv
geoinsights_3d-1.1012.dist-info/licenses/license
geoinsights_3d-1.1012.dist-info/METADATA
geoinsights_3d-1.1012.dist-info/WHEEL
geoinsights_3d-1.1012.dist-info/entry_points.txt
geoinsights_3d-1.1012.dist-info/top_level.txt
geoinsights_3d-1.1012.dist-info/RECORD
