Metadata-Version: 2.4
Name: geoinsights-3d
Version: 1.1012
Summary: Rapid drilling data visualisation and analysis for geologists with AI.
Author-email: Gavin Chapman <gavinjchapman@gmail.com>
Project-URL: Homepage, https://github.com/chapmangj/geoinsights3d
Project-URL: Tutorial, https://medium.com/@gavinjchapman/geoinsights-3d-rapid-drilling-data-visualisation-and-analysis-for-geologists-with-ai-1163b4039bb1
Project-URL: User Guide, https://github.com/chapmangj/geoinsights3d/blob/main/GeoInsights%203D%20User%20Guide.pdf
Classifier: Programming Language :: Python :: 3
Classifier: License :: OSI Approved :: MIT License
Classifier: Operating System :: OS Independent
Classifier: Topic :: Scientific/Engineering :: GIS
Requires-Python: >=3.9
License-File: license
Requires-Dist: streamlit
Requires-Dist: pandas
Requires-Dist: numpy
Requires-Dist: plotly
Requires-Dist: google-genai
Requires-Dist: scikit-learn
Requires-Dist: Pillow
Requires-Dist: matplotlib
Requires-Dist: shap
Requires-Dist: tensorflow
Requires-Dist: scikit-image
Dynamic: license-file
